dol_cookbook/__init__.py
dol_cookbook/pipes.py
dol_cookbook/util.py
dol_cookbook-0.1.7.dist-info/LICENSE
dol_cookbook-0.1.7.dist-info/METADATA
dol_cookbook-0.1.7.dist-info/WHEEL
dol_cookbook-0.1.7.dist-info/top_level.txt
dol_cookbook-0.1.7.dist-info/RECORD
