Metadata-Version: 2.1
Name: dol-cookbook
Version: 0.1.7
Summary: recipes for dol tools
License: mit
License-File: LICENSE
